buyback/__init__.py
buyback/benchmark.py
buyback/constants.py
buyback/monte_carlo.py
buyback/strategy.py
buyback/volatility.py
buyback/volume.py
buyback-0.1.2.dist-info/LICENSE
buyback-0.1.2.dist-info/METADATA
buyback-0.1.2.dist-info/WHEEL
buyback-0.1.2.dist-info/RECORD
